action_hero/__init__.py
action_hero/lib.py
action_hero/py.typed
action_hero/actions/__init__.py
action_hero/actions/queue_celery.py
action_hero/actions/simple.py
django_admin_action_hero-0.1.1.dist-info/METADATA
django_admin_action_hero-0.1.1.dist-info/WHEEL
django_admin_action_hero-0.1.1.dist-info/licenses/LICENSE
django_admin_action_hero-0.1.1.dist-info/RECORD
