Metadata-Version: 2.4
Name: django-admin-action-hero
Version: 0.1.1
Summary: Django admin actions made more generic.  Easily create reusable admin actions for common tasks. Provides two usable implementations and an ABC for creating your own implementations.
Project-URL: Documentation, https://django-admin-action-hero.readthedocs.io/en/latest/
Project-URL: Repository, https://github.com/kennethlove/django-admin-action-hero
Author-email: Kenneth Love <11908+kennethlove@users.noreply.github.com>
License:                                  Apache License
License-File: LICENSE
Keywords: action,admin,celery,django,task
Classifier: Development Status :: 4 - Beta
Classifier: Framework :: Django
Classifier: Framework :: Django :: 4.2
Classifier: Framework :: Django :: 5.2
Classifier: Framework :: Django :: 6.0
Classifier: Intended Audience :: Developers
Classifier: License :: OSI Approved :: Apache Software License
Classifier: Programming Language :: Python :: 3
Classifier: Programming Language :: Python :: 3 :: Only
Classifier: Programming Language :: Python :: 3.12
Classifier: Programming Language :: Python :: 3.13
Classifier: Programming Language :: Python :: 3.14
Classifier: Topic :: Software Development :: Libraries
Classifier: Typing :: Typed
Requires-Python: >=3.12
Requires-Dist: django>=4.2.26
Provides-Extra: celery
Requires-Dist: celery>=5.5.3; extra == 'celery'
